abnormal_hieratic_indexer/__init__.py
abnormal_hieratic_indexer/index_annotations.py
abnormal_hieratic_indexer-1.1.2.dist-info/METADATA
abnormal_hieratic_indexer-1.1.2.dist-info/WHEEL
abnormal_hieratic_indexer-1.1.2.dist-info/entry_points.txt
abnormal_hieratic_indexer-1.1.2.dist-info/licenses/LICENSE
abnormal_hieratic_indexer-1.1.2.dist-info/RECORD
