Metadata-Version: 2.4
Name: abnormal-hieratic-indexer
Version: 1.1.2
Summary: Index annotations from the Abnormal Hieratic Global Portal in Elasticsearch
Project-URL: Documentation, https://github.com/LeidenUniversityLibrary/abnormal-hieratic-indexer#readme
Project-URL: Issues, https://github.com/LeidenUniversityLibrary/abnormal-hieratic-indexer/issues
Project-URL: Source, https://github.com/LeidenUniversityLibrary/abnormal-hieratic-indexer
Author-email: Ben Companjen <ben@companjen.name>
License-Expression: GPL-3.0-or-later
License-File: LICENSE
Classifier: Development Status :: 4 - Beta
Classifier: Programming Language :: Python
Classifier: Programming Language :: Python :: 3.9
Classifier: Programming Language :: Python :: 3.10
Classifier: Programming Language :: Python :: 3.11
Classifier: Programming Language :: Python :: 3.12
Classifier: Programming Language :: Python :: 3.13
Classifier: Programming Language :: Python :: Implementation :: CPython
Classifier: Programming Language :: Python :: Implementation :: PyPy
Requires-Python: >=3.9
Requires-Dist: beautifulsoup4~=4.12.3
Requires-Dist: requests~=2.32.3
